ghost_mcp/__init__.py
ghost_mcp/client.py
ghost_mcp/config.py
ghost_mcp/server.py
ghost_mcp/auth/__init__.py
ghost_mcp/auth/admin_auth.py
ghost_mcp/auth/content_auth.py
ghost_mcp/tools/__init__.py
ghost_mcp/tools/admin/__init__.py
ghost_mcp/tools/admin/authors.py
ghost_mcp/tools/admin/media.py
ghost_mcp/tools/admin/members.py
ghost_mcp/tools/admin/pages.py
ghost_mcp/tools/admin/posts.py
ghost_mcp/tools/admin/settings.py
ghost_mcp/tools/admin/tags.py
ghost_mcp/tools/content/__init__.py
ghost_mcp/tools/content/authors.py
ghost_mcp/tools/content/pages.py
ghost_mcp/tools/content/posts.py
ghost_mcp/tools/content/settings.py
ghost_mcp/tools/content/tags.py
ghost_mcp/types/__init__.py
ghost_mcp/types/errors.py
ghost_mcp/types/ghost.py
ghost_mcp/types/mcp.py
ghost_mcp/utils/__init__.py
ghost_mcp/utils/content_validation.py
ghost_mcp/utils/logging.py
ghost_mcp/utils/retry.py
ghost_mcp/utils/validation.py
ghost_mcp-0.2.0.dist-info/METADATA
ghost_mcp-0.2.0.dist-info/WHEEL
ghost_mcp-0.2.0.dist-info/entry_points.txt
ghost_mcp-0.2.0.dist-info/RECORD
